Workbook

Sheet Scenario Summary
B2: Salesforce Scenario Comparison
B3: FY29 estimated outcomes; USD millions except percentages
B5: Metric | C5: Downside | D5: Base | E5: Upside | N5: Metric | O5: Downside | P5: Base | Q5: Upside
B6: Revenue | C6: =Actuals!H8*(1+Assumptions!D28)*(1+Assumptions!E28)*(1+Assumptions!F28) -> 46705.659 | D6: =Actuals!H8*(1+Assumptions!D8)*(1+Assumptions!E8)*(1+Assumptions!F8) -> 53282.721 | E6: =Actuals!H8*(1+Assumptions!D18)*(1+Assumptions!E18)*(1+Assumptions!F18) -> 56786.268 | N6: Revenue | O6: =C6 -> 46705.659 | P6: =D6 -> 53282.721 | Q6: =E6 -> 56786.268
B7: Revenue growth | C7: =Assumptions!F28 -> 0.03 | D7: =Assumptions!F8 -> 0.08 | E7: =Assumptions!F18 -> 0.1 | N7: Operating income | O7: =C8 -> 7406.4337 | P7: =D8 -> 14173.204 | Q7: =E8 -> 16922.308
B8: Operating income | C8: =C6*C9 -> 7406.4337 | D8: =D6*D9 -> 14173.204 | E8: =E6*E9 -> 16922.308 | N8: Free cash flow | O8: =C10 -> 13077.585 | P8: =D10 -> 19981.02 | Q8: =E10 -> 23282.37
B9: Operating margin | C9: =Assumptions!F29-Assumptions!F30-Assumptions!F31-Assumptions!F32-Assumptions!F33/C6 -> 0.1585768 | D9: =Assumptions!F9-Assumptions!F10-Assumptions!F11-Assumptions!F12-Assumptions!F13/D6 -> 0.266 | E9: =Assumptions!F19-Assumptions!F20-Assumptions!F21-Assumptions!F22-Assumptions!F23/E6 -> 0.298
B10: Free cash flow | C10: =C6*C11 -> 13077.585 | D10: =D6*D11 -> 19981.02 | E10: =E6*E11 -> 23282.37
B11: Free cash flow margin | C11: =Assumptions!F34 -> 0.28 | D11: =Assumptions!F14 -> 0.375 | E11: =Assumptions!F24 -> 0.41 | N11: Metric | O11: Downside | P11: Base | Q11: Upside
B12: Rule of 40 | C12: =C7+C11 -> 0.31 | D12: =D7+D11 -> 0.455 | E12: =E7+E11 -> 0.51 | N12: Revenue growth | O12: =C7 -> 0.03 | P12: =D7 -> 0.08 | Q12: =E7 -> 0.1
N13: Operating margin | O13: =C9 -> 0.1585768 | P13: =D9 -> 0.266 | Q13: =E9 -> 0.298
N14: Free cash flow margin | O14: =C11 -> 0.28 | P14: =D11 -> 0.375 | Q14: =E11 -> 0.41
N15: Rule of 40 | O15: =C12 -> 0.31 | P15: =D12 -> 0.455 | Q15: =E12 -> 0.51
B34: Management takeaways
B35: Base case | C35: Revenue reaches $53.3B with a 26.6% operating margin, a 37.5% free cash flow margin, and a 45.5% Rule of 40 result.
B36: Downside risk | C36: Revenue growth slows to 3.0%, operating margin falls to 15.9%, and the Rule of 40 declines to 31.0%.
B37: Upside potential | C37: Revenue reaches $56.8B with a 29.8% operating margin and a 51.0% Rule of 40 result.
B38: Management focus | C38: Protect sales efficiency and adjust operating expenses early if revenue growth begins moving toward the downside case.

Sheet Assumptions
B2: Salesforce Forecast Assumptions
B3: USD millions except percentages
B5: Driver | C5: FY26A | D5: FY27E | E5: FY28E | F5: FY29E | G5: Scenario logic
B7: Base case | G7: Recent growth continues with gradual margin expansion
B8: Revenue growth | C8: =Actuals!H9 -> 0.095791001 | D8: 0.09 | E8: 0.09 | F8: 0.08
B9: Gross margin | C9: =Actuals!H16 -> 0.77676099 | D9: 0.78 | E9: 0.785 | F9: 0.79
B10: R&D as % of revenue | C10: =Actuals!H18/Actuals!H8 -> 0.1443227 | D10: 0.142 | E10: 0.14 | F10: 0.138
B11: Sales & marketing as % of revenue | C11: =Actuals!H19/Actuals!H8 -> 0.34545455 | D11: 0.34 | E11: 0.33 | F11: 0.32
B12: G&A as % of revenue | C12: =Actuals!H20/Actuals!H8 -> 0.072245635 | D12: 0.07 | E12: 0.068 | F12: 0.066
B13: Restructuring expense | C13: =Actuals!H21 -> 586 | D13: 300 | E13: 150 | F13: 0
B14: Free cash flow margin | C14: =Actuals!H31 -> 0.34682721 | D14: 0.355 | E14: 0.365 | F14: 0.375
B17: Upside Case | G17: Stronger demand and faster operating leverage
B18: Revenue growth | C18: =$C8 -> 0.095791001 | D18: 0.12 | E18: 0.11 | F18: 0.1
B19: Gross margin | C19: =$C9 -> 0.77676099 | D19: 0.785 | E19: 0.792 | F19: 0.8
B20: R&D as % of revenue | C20: =$C10 -> 0.1443227 | D20: 0.14 | E20: 0.138 | F20: 0.135
B21: Sales & marketing as % of revenue | C21: =$C11 -> 0.34545455 | D21: 0.335 | E21: 0.32 | F21: 0.305
B22: G&A as % of revenue | C22: =$C12 -> 0.072245635 | D22: 0.068 | E22: 0.065 | F22: 0.062
B23: Restructuring expense | C23: =$C13 -> 586 | D23: 150 | E23: 0 | F23: 0
B24: Free cash flow margin | C24: =$C14 -> 0.34682721 | D24: 0.37 | E24: 0.39 | F24: 0.41
B27: Downside Case | G27: Slower demand, margin pressure, and additional restructuring
B28: Revenue growth | C28: =$C8 -> 0.095791001 | D28: 0.05 | E28: 0.04 | F28: 0.03
B29: Gross margin | C29: =$C9 -> 0.77676099 | D29: 0.77 | E29: 0.765 | F29: 0.76
B30: R&D as % of revenue | C30: =$C10 -> 0.1443227 | D30: 0.148 | E30: 0.15 | F30: 0.15
B31: Sales & marketing as % of revenue | C31: =$C11 -> 0.34545455 | D31: 0.355 | E31: 0.36 | F31: 0.365
B32: G&A as % of revenue | C32: =$C12 -> 0.072245635 | D32: 0.075 | E32: 0.077 | F32: 0.08
B33: Restructuring expense | C33: =$C13 -> 586 | D33: 800 | E33: 600 | F33: 300
B34: Free cash flow margin | C34: =$C14 -> 0.34682721 | D34: 0.31 | E34: 0.29 | F34: 0.28

Sheet Forecast
B2: Salesforce Financial Forecast
B3: Selected Scenario; USD millions except percentages
B4: Selected Scenario | C4: Base
B5: =$C$4&" case forecast" -> Base case forecast
B6: Metric | C6: FY26A | D6: FY27E | E6: FY28E | F6: FY29E
B8: Revenue | C8: =Actuals!H8 -> 41525 | D8: =C8*(1+D9) -> 45262.25 | E8: =D8*(1+E9) -> 49335.853 | F8: =E8*(1+F9) -> 53282.721
B9: Revenue growth | C9: =Actuals!H9 -> 0.095791001 | D9: =IF($C$4="Base",Assumptions!D8,IF($C$4="Upside",Assumptions!D18,Assumptions!D28)) -> 0.09 | E9: =IF($C$4="Base",Assumptions!E8,IF($C$4="Upside",Assumptions!E18,Assumptions!E28)) -> 0.09 | F9: =IF($C$4="Base",Assumptions!F8,IF($C$4="Upside",Assumptions!F18,Assumptions!F28)) -> 0.08
B11: Gross profit | C11: =Actuals!H15 -> 32255 | D11: =D8*IF($C$4="Base",Assumptions!D9,IF($C$4="Upside",Assumptions!D19,Assumptions!D29)) -> 35304.555 | E11: =E8*IF($C$4="Base",Assumptions!E9,IF($C$4="Upside",Assumptions!E19,Assumptions!E29)) -> 38728.644 | F11: =F8*IF($C$4="Base",Assumptions!F9,IF($C$4="Upside",Assumptions!F19,Assumptions!F29)) -> 42093.349
B12: Gross margin | C12: =Actuals!H16 -> 0.77676099 | D12: =D11/D8 -> 0.78 | E12: =E11/E8 -> 0.785 | F12: =F11/F8 -> 0.79
B14: Research & development | C14: =Actuals!H18 -> 5993 | D14: =D8*IF($C$4="Base",Assumptions!D10,IF($C$4="Upside",Assumptions!D20,Assumptions!D30)) -> 6427.2395 | E14: =E8*IF($C$4="Base",Assumptions!E10,IF($C$4="Upside",Assumptions!E20,Assumptions!E30)) -> 6907.0194 | F14: =F8*IF($C$4="Base",Assumptions!F10,IF($C$4="Upside",Assumptions!F20,Assumptions!F30)) -> 7353.0155
B15: Sales & marketing | C15: =Actuals!H19 -> 14345 | D15: =D8*IF($C$4="Base",Assumptions!D11,IF($C$4="Upside",Assumptions!D21,Assumptions!D31)) -> 15389.165 | E15: =E8*IF($C$4="Base",Assumptions!E11,IF($C$4="Upside",Assumptions!E21,Assumptions!E31)) -> 16280.831 | F15: =F8*IF($C$4="Base",Assumptions!F11,IF($C$4="Upside",Assumptions!F21,Assumptions!F31)) -> 17050.471
B16: General & administrative | C16: =Actuals!H20 -> 3000 | D16: =D8*IF($C$4="Base",Assumptions!D12,IF($C$4="Upside",Assumptions!D22,Assumptions!D32)) -> 3168.3575 | E16: =E8*IF($C$4="Base",Assumptions!E12,IF($C$4="Upside",Assumptions!E22,Assumptions!E32)) -> 3354.838 | F16: =F8*IF($C$4="Base",Assumptions!F12,IF($C$4="Upside",Assumptions!F22,Assumptions!F32)) -> 3516.6596
B17: Restructuring | C17: =Actuals!H21 -> 586 | D17: =IF($C$4="Base",Assumptions!D13,IF($C$4="Upside",Assumptions!D23,Assumptions!D33)) -> 300 | E17: =IF($C$4="Base",Assumptions!E13,IF($C$4="Upside",Assumptions!E23,Assumptions!E33)) -> 150 | F17: =IF($C$4="Base",Assumptions!F13,IF($C$4="Upside",Assumptions!F23,Assumptions!F33)) -> 0
B18: Total operating expenses | C18: =Actuals!H22 -> 23924 | D18: =SUM(D14:D17) -> 25284.762 | E18: =SUM(E14:E17) -> 26692.689 | F18: =SUM(F14:F17) -> 27920.146
B19: Operating income | C19: =Actuals!H23 -> 8331 | D19: =D11-D18 -> 10019.793 | E19: =E11-E18 -> 12035.956 | F19: =F11-F18 -> 14173.204
B20: Operating margin | C20: =Actuals!H24 -> 0.20062613 | D20: =D19/D8 -> 0.22137196 | E20: =E19/E8 -> 0.24395961 | F20: =F19/F8 -> 0.266
B22: Free cash flow | C22: =Actuals!H30 -> 14402 | D22: =D8*D23 -> 16068.099 | E22: =E8*E23 -> 18007.586 | F22: =F8*F23 -> 19981.02
B23: Free cash flow margin | C23: =Actuals!H31 -> 0.34682721 | D23: =IF($C$4="Base",Assumptions!D14,IF($C$4="Upside",Assumptions!D24,Assumptions!D34)) -> 0.355 | E23: =IF($C$4="Base",Assumptions!E14,IF($C$4="Upside",Assumptions!E24,Assumptions!E34)) -> 0.365 | F23: =IF($C$4="Base",Assumptions!F14,IF($C$4="Upside",Assumptions!F24,Assumptions!F34)) -> 0.375
B24: Rule of 40 | C24: =Actuals!H35 -> 0.44261821 | D24: =D9+D23 -> 0.445 | E24: =E9+E23 -> 0.455 | F24: =F9+F23 -> 0.455

Sheet Actuals
C2: Salesforce Historical Operating Performance
C3: Fiscal years ended January 31; USD Millions
C5: Metric | D5: FY22A | E5: FY23A | F5: FY24A | G5: FY25A | H5: FY26A
C6: Subscription revenue | D6: ='Raw Actuals'!C2 -> 24657 | E6: ='Raw Actuals'!C3 -> 29021 | F6: ='Raw Actuals'!C4 -> 32537 | G6: ='Raw Actuals'!C5 -> 35679 | H6: ='Raw Actuals'!C6 -> 39388
C7: Professional services revenue | D7: ='Raw Actuals'!D2 -> 1835 | E7: ='Raw Actuals'!D3 -> 2331 | F7: ='Raw Actuals'!D4 -> 2320 | G7: ='Raw Actuals'!D5 -> 2216 | H7: ='Raw Actuals'!D6 -> 2137
C8: Total revenue | D8: =SUM(D6:D7) -> 26492 | E8: =SUM(E6:E7) -> 31352 | F8: =SUM(F6:F7) -> 34857 | G8: =SUM(G6:G7) -> 37895 | H8: =SUM(H6:H7) -> 41525
C9: Revenue growth | D9: (no prev yr) | E9: =E8 / D8 -1 -> 0.18345161 | F9: =F8 / E8 -1 -> 0.1117951 | G9: =G8 / F8 -1 -> 0.087156095 | H9: =H8 / G8 -1 -> 0.095791001
C10: Subscription mix | D10: =D6/D8 -> 0.93073381 | E10: =E6/E8 -> 0.92565068 | F10: =F6/F8 -> 0.93344235 | G10: =G6/G8 -> 0.94152263 | H10: =H6/H8 -> 0.94853703
C12: Subscription cost | D12: ='Raw Actuals'!E2 -> 5059 | E12: ='Raw Actuals'!E3 -> 5821 | F12: ='Raw Actuals'!E4 -> 6177 | G12: ='Raw Actuals'!E5 -> 6198 | H12: ='Raw Actuals'!E6 -> 6796
C13: Professional services cost | D13: ='Raw Actuals'!F2 -> 1967 | E13: ='Raw Actuals'!F3 -> 2539 | F13: ='Raw Actuals'!F4 -> 2364 | G13: ='Raw Actuals'!F5 -> 2445 | H13: ='Raw Actuals'!F6 -> 2474
C14: Total cost of revenue | D14: =SUM(D12:D13) -> 7026 | E14: =SUM(E12:E13) -> 8360 | F14: =SUM(F12:F13) -> 8541 | G14: =SUM(G12:G13) -> 8643 | H14: =SUM(H12:H13) -> 9270
C15: Gross profit | D15: =D8-D14 -> 19466 | E15: =E8-E14 -> 22992 | F15: =F8-F14 -> 26316 | G15: =G8-G14 -> 29252 | H15: =H8-H14 -> 32255
C16: Gross margin | D16: =D15/D8 -> 0.73478786 | E16: =E15/E8 -> 0.73335034 | F16: =F15/F8 -> 0.75497031 | G16: =G15/G8 -> 0.77192242 | H16: =H15/H8 -> 0.77676099
C18: Research & development | D18: ='Raw Actuals'!G2 -> 4465 | E18: ='Raw Actuals'!G3 -> 5055 | F18: ='Raw Actuals'!G4 -> 4906 | G18: ='Raw Actuals'!G5 -> 5493 | H18: ='Raw Actuals'!G6 -> 5993
C19: Sales & marketing | D19: ='Raw Actuals'!H2 -> 11855 | E19: ='Raw Actuals'!H3 -> 13526 | F19: ='Raw Actuals'!H4 -> 12877 | G19: ='Raw Actuals'!H5 -> 13257 | H19: ='Raw Actuals'!H6 -> 14345
C20: General & administrative | D20: ='Raw Actuals'!I2 -> 2598 | E20: ='Raw Actuals'!I3 -> 2553 | F20: ='Raw Actuals'!I4 -> 2534 | G20: ='Raw Actuals'!I5 -> 2836 | H20: ='Raw Actuals'!I6 -> 3000
C21: Restructuring | D21: ='Raw Actuals'!J2 -> 0 | E21: ='Raw Actuals'!J3 -> 828 | F21: ='Raw Actuals'!J4 -> 988 | G21: ='Raw Actuals'!J5 -> 461 | H21: ='Raw Actuals'!J6 -> 586
C22: Total operating expenses | D22: =SUM(D18:D21) -> 18918 | E22: =SUM(E18:E21) -> 21962 | F22: =SUM(F18:F21) -> 21305 | G22: =SUM(G18:G21) -> 22047 | H22: =SUM(H18:H21) -> 23924
C23: Operating income | D23: =D15-D22 -> 548 | E23: =E15-E22 -> 1030 | F23: =F15-F22 -> 5011 | G23: =G15-G22 -> 7205 | H23: =H15-H22 -> 8331
C24: Operating margin | D24: =D23/D8 -> 0.02068549 | E24: =E23/E8 -> 0.032852769 | F24: =F23/F8 -> 0.14375879 | G24: =G23/G8 -> 0.19013062 | H24: =H23/H8 -> 0.20062613
C26: Net income | D26: {=INDEX('Raw Actuals'!$L$2:$L$6,COLUMNS($D:D))} -> 1444 | E26: {=INDEX('Raw Actuals'!$L$2:$L$6,COLUMNS($D:E))} -> 208 | F26: {=INDEX('Raw Actuals'!$L$2:$L$6,COLUMNS($D:F))} -> 4136 | G26: {=INDEX('Raw Actuals'!$L$2:$L$6,COLUMNS($D:G))} -> 6197 | H26: {=INDEX('Raw Actuals'!$L$2:$L$6,COLUMNS($D:H))} -> 7457
C28: Operating cash flow | D28: {=INDEX('Raw Actuals'!$M$2:$M$6,COLUMNS($D:D))} -> 6000 | E28: {=INDEX('Raw Actuals'!$M$2:$M$6,COLUMNS($D:E))} -> 7111 | F28: {=INDEX('Raw Actuals'!$M$2:$M$6,COLUMNS($D:F))} -> 10234 | G28: {=INDEX('Raw Actuals'!$M$2:$M$6,COLUMNS($D:G))} -> 13092 | H28: {=INDEX('Raw Actuals'!$M$2:$M$6,COLUMNS($D:H))} -> 14996
C29: Capital expenditures | D29: {=INDEX('Raw Actuals'!$N$2:$N$6,COLUMNS($D:D))} -> 717 | E29: {=INDEX('Raw Actuals'!$N$2:$N$6,COLUMNS($D:E))} -> 798 | F29: {=INDEX('Raw Actuals'!$N$2:$N$6,COLUMNS($D:F))} -> 736 | G29: {=INDEX('Raw Actuals'!$N$2:$N$6,COLUMNS($D:G))} -> 658 | H29: {=INDEX('Raw Actuals'!$N$2:$N$6,COLUMNS($D:H))} -> 594
C30: Free cash flow | D30: =D28-D29 -> 5283 | E30: =E28-E29 -> 6313 | F30: =F28-F29 -> 9498 | G30: =G28-G29 -> 12434 | H30: =H28-H29 -> 14402
C31: Free cash flow margin | D31: =D30/D8 -> 0.19941869 | E31: =E30/E8 -> 0.20135876 | F31: =F30/F8 -> 0.27248472 | G31: =G30/G8 -> 0.32811717 | H31: =H30/H8 -> 0.34682721
C33: Stock-based compensation | D33: {=INDEX('Raw Actuals'!$O$2:$O$6,COLUMNS($D:D))} -> 2779 | E33: {=INDEX('Raw Actuals'!$O$2:$O$6,COLUMNS($D:E))} -> 3279 | F33: {=INDEX('Raw Actuals'!$O$2:$O$6,COLUMNS($D:F))} -> 2787 | G33: {=INDEX('Raw Actuals'!$O$2:$O$6,COLUMNS($D:G))} -> 3183 | H33: {=INDEX('Raw Actuals'!$O$2:$O$6,COLUMNS($D:H))} -> 3509
C34: Stock-based compensation as % of revenue | D34: =D33/D8 -> 0.10489959 | E34: =E33/E8 -> 0.10458663 | F34: =F33/F8 -> 0.079955246 | G34: =G33/G8 -> 0.08399525 | H34: =H33/H8 -> 0.084503311
C35: Rule of 40 | D35: (no prev yr) | E35: =E9+E31 -> 0.38481037 | F35: =F9+F31 -> 0.38427982 | G35: =G9+G31 -> 0.41527326 | H35: =H9+H31 -> 0.44261821
C37: Operating income check | D37: =D23-'Raw Actuals'!K2 -> 0 | E37: =E23-'Raw Actuals'!K3 -> 0 | F37: =F23-'Raw Actuals'!K4 -> 0 | G37: =G23-'Raw Actuals'!K5 -> 0 | H37: =H23-'Raw Actuals'!K6 -> 0

Sheet Raw Actuals
A1: Fiscal Year Ended | B1: Fiscal Year | C1: Subscription Revenue | D1: Professional Services Revenue | E1: Subscription Cost | F1: Professional Services Cost | G1: Research & Development | H1: Sales & Marketing | I1: General & Administrative | J1: Restructuring | K1: Reported Operating Income | L1: Net Income | M1: Operating Cash Flow | N1: Capital Expenditures | O1: Stock-Based Compensation
A2: 44592 | B2: FY22 | C2: 24657 | D2: 1835 | E2: 5059 | F2: 1967 | G2: 4465 | H2: 11855 | I2: 2598 | J2: 0 | K2: 548 | L2: 1444 | M2: 6000 | N2: 717 | O2: 2779
A3: 44957 | B3: FY23 | C3: 29021 | D3: 2331 | E3: 5821 | F3: 2539 | G3: 5055 | H3: 13526 | I3: 2553 | J3: 828 | K3: 1030 | L3: 208 | M3: 7111 | N3: 798 | O3: 3279
A4: 45322 | B4: FY24 | C4: 32537 | D4: 2320 | E4: 6177 | F4: 2364 | G4: 4906 | H4: 12877 | I4: 2534 | J4: 988 | K4: 5011 | L4: 4136 | M4: 10234 | N4: 736 | O4: 2787
A5: 45688 | B5: FY25 | C5: 35679 | D5: 2216 | E5: 6198 | F5: 2445 | G5: 5493 | H5: 13257 | I5: 2836 | J5: 461 | K5: 7205 | L5: 6197 | M5: 13092 | N5: 658 | O5: 3183
A6: 46053 | B6: FY26 | C6: 39388 | D6: 2137 | E6: 6796 | F6: 2474 | G6: 5993 | H6: 14345 | I6: 3000 | J6: 586 | K6: 8331 | L6: 7457 | M6: 14996 | N6: 594 | O6: 3509
A9: Source documentation
A10: FY26 Form 10-K | B10: =HYPERLINK("https://www.sec.gov/Archives/edgar/data/1108524/000110852426000060/crm-20260131.htm","Salesforce FY26 Form 10-K") -> Salesforce FY26 Form 10-K
A11: FY24 Form 10-K | B11: =HYPERLINK("https://www.sec.gov/Archives/edgar/data/1108524/000110852424000005/crm-20240131.htm","Salesforce FY24 Form 10-K") -> Salesforce FY24 Form 10-K
A12: SEC Companyfacts | B12: =HYPERLINK("https://data.sec.gov/api/xbrl/companyfacts/CIK0001108524.json","Salesforce SEC Companyfacts") -> Salesforce SEC Companyfacts
A14: Metric definitions and methodology
A15: Free cash flow | B15: Operating cash flow less capital expenditures
A16: Free cash flow margin | B16: Free cash flow divided by total revenue
A17: Rule of 40 | B17: Revenue growth plus free cash flow margin
A18: Forecast approach | B18: Base, upside, and downside assumptions are anchored to historical trends and are not Salesforce management guidance
A19: Units and period | B19: USD millions except percentages; fiscal years end January 31
A20: Model limitation | B20: Free cash flow is estimated using a scenario-level free cash flow margin applied to revenue. The model does not separately forecast operating cash flow or capital expenditures.
